efmlrs/__init__.py
efmlrs/_version.py
efmlrs/post.py
efmlrs/pre.py
efmlrs/quickcheck_sbml.py
efmlrs/postprocessing/__init__.py
efmlrs/postprocessing/decompressing.py
efmlrs/postprocessing/get_data.py
efmlrs/postprocessing/decompressions/__init__.py
efmlrs/postprocessing/decompressions/deadend.py
efmlrs/postprocessing/decompressions/many2one.py
efmlrs/postprocessing/decompressions/nullspace.py
efmlrs/preprocessing/__init__.py
efmlrs/preprocessing/boundaries.py
efmlrs/preprocessing/get_data.py
efmlrs/preprocessing/mplrs_output.py
efmlrs/preprocessing/compressions/__init__.py
efmlrs/preprocessing/compressions/deadend.py
efmlrs/preprocessing/compressions/echelon.py
efmlrs/preprocessing/compressions/many2one.py
efmlrs/preprocessing/compressions/nullspace.py
efmlrs/util/__init__.py
efmlrs/util/convert_matrix.py
efmlrs/util/data.py
efmlrs/util/log.py
efmlrs-2.3.6.dist-info/AUTHORS.rst
efmlrs-2.3.6.dist-info/LICENSE
efmlrs-2.3.6.dist-info/METADATA
efmlrs-2.3.6.dist-info/WHEEL
efmlrs-2.3.6.dist-info/entry_points.txt
efmlrs-2.3.6.dist-info/top_level.txt
efmlrs-2.3.6.dist-info/RECORD
