Metadata-Version: 2.1
Name: efmlrs
Version: 2.3.6
Summary: Extracts EFMs from result file of mplrs and decompresses EFMs from efmtool and mplrs results that have been compressed with EFMlrs
Home-page: https://github.com/BeeAnka/EFMlrs
Author: Bianca Buchner
Author-email: bianca.buchner@gmail.com
License: GPLv3
Platform: UNKNOWN
Classifier: Development Status :: 4 - Beta
Classifier: Intended Audience :: Developers
Classifier: License :: OSI Approved :: GNU General Public License (GPL)
Classifier: Natural Language :: English
Classifier: Programming Language :: Python :: 3.7
Requires-Dist: cobra (==0.17.1)
Requires-Dist: numpy (==1.18.1)
Requires-Dist: pandas (==1.0.1)
Requires-Dist: sympy (==1.5.1)
